code_listing_generator/__init__.py
code_listing_generator/template.tex
code_listing_generator-0.1.2.dist-info/LICENSE
code_listing_generator-0.1.2.dist-info/METADATA
code_listing_generator-0.1.2.dist-info/WHEEL
code_listing_generator-0.1.2.dist-info/entry_points.txt
code_listing_generator-0.1.2.dist-info/top_level.txt
code_listing_generator-0.1.2.dist-info/RECORD
